qradar/__init__.py
qradar/api/__init__.py
qradar/api/client.py
qradar/api/endpoints/__init__.py
qradar/api/endpoints/access.py
qradar/api/endpoints/ariel.py
qradar/api/endpoints/config.py
qradar/models/__init__.py
qradar/models/custom_property.py
qradar/models/domain.py
qradar/models/event_collector.py
qradar/models/log_source.py
qradar/models/log_source_group.py
qradar/models/log_source_type.py
qradar/models/login_attempt.py
qradar/models/network_hierarchy.py
qradar/models/qradarmodel.py
qradar/models/saved_search_group.py
qradar_api-0.0.6.dist-info/LICENSE
qradar_api-0.0.6.dist-info/METADATA
qradar_api-0.0.6.dist-info/WHEEL
qradar_api-0.0.6.dist-info/top_level.txt
qradar_api-0.0.6.dist-info/RECORD
