Metadata-Version: 2.1
Name: qradar-api
Version: 0.0.6
Summary: An object-based approach to the QRadar Client API
Home-page: https://github.com/dpb-infosec/qradar-lib
Author: Thisisnottheuseryouarelookingfor
Author-email: nottheuseryouarelookingfor@gmail.com
License: UNKNOWN
Project-URL: Bug Tracker, https://github.com/dpb-infosec/qradar-lib/issues
Platform: UNKNOWN
Classifier: Programming Language :: Python :: 3
Classifier: Development Status :: 3 - Alpha
Classifier: License :: OSI Approved :: GNU General Public License v3 or later (GPLv3+)
Classifier: Operating System :: OS Independent
Requires-Python: >=3.6
Requires-Dist: requests
